nb_to_src/__init__.py
nb_to_src/converter.py
nb_to_src/py.typed
py_nb_to_src-0.3.0.dist-info/licenses/LICENSE
tests/__init__.py
tests/test_converter.py
tests/fixtures/sample.Rmd
tests/fixtures/sample_python.ipynb
tests/fixtures/sample_r.ipynb
py_nb_to_src-0.3.0.dist-info/METADATA
py_nb_to_src-0.3.0.dist-info/WHEEL
py_nb_to_src-0.3.0.dist-info/top_level.txt
py_nb_to_src-0.3.0.dist-info/RECORD
