Metadata-Version: 2.4
Name: py-nb-to-src
Version: 0.3.0
Summary: Convert Jupyter Notebooks (of all languages) and Rmd to their non-notebook counterparts.
Author-email: Eva Maxfield Brown <evamxb@uw.edu>
License: MPLv2 License
Project-URL: Homepage, https://github.com/evamaxfield/py-nb-to-src
Project-URL: Bug Tracker, https://github.com/evamaxfield/py-nb-to-src/issues
Project-URL: Documentation, https://evamaxfield.github.io/py-nb-to-src
Project-URL: User Support, https://github.com/evamaxfield/py-nb-to-src/issues
Classifier: Development Status :: 4 - Beta
Classifier: Natural Language :: English
Classifier: Programming Language :: Python :: 3.12
Classifier: Programming Language :: Python :: 3.13
Classifier: Programming Language :: Python :: 3.14
Requires-Python: >=3.12
License-File: LICENSE
Requires-Dist: nbconvert>=7
Requires-Dist: tqdm>=4
Provides-Extra: dev
Requires-Dist: pytest>=8; extra == "dev"
Provides-Extra: lint
Requires-Dist: prek>=0.2.29; extra == "lint"
Requires-Dist: ty>=0.0.12; extra == "lint"
Dynamic: license-file
